Metadata-Version: 2.1
Name: odoo8-addon-account-banking-fr-lcr
Version: 8.0.0.1.0.99.dev36
Summary: Create French LCR CFONB files
Home-page: http://www.akretion.com
Author: Akretion,Odoo Community Association (OCA)
Author-email: support@odoo-community.org
License: AGPL-3
Platform: UNKNOWN
Classifier: Programming Language :: Python
Classifier: Framework :: Odoo
Classifier: Framework :: Odoo :: 8.0
Classifier: License :: OSI Approved :: GNU Affero General Public License v3
Requires-Python: ~=2.7
Requires-Dist: odoo8-addon-account-direct-debit
Requires-Dist: odoo (<9.0a,>=8.0a)
Requires-Dist: unidecode
